{
  "kind": "collectionType",
  "collectionName": "tags",
  "info": {
    "singularName": "tag",
    "pluralName": "tags",
    "displayName": "Tags",
    "description": ""
  },
  "options": {
    "draftAndPublish": true
  },
  "pluginOptions": {},
  "attributes": {
    "name": {
      "type": "string",
      "unique": true,
      "required": true
    },
    "colour": {
      "type": "string"
    },
    "icon": {
      "type": "media",
      "multiple": false,
      "required": false,
      "allowedTypes": [
        "images",
        "files",
        "videos",
        "audios"
      ]
    },
    "projects": {
      "type": "relation",
      "relation": "manyToMany",
      "target": "api::project.project",
      "inversedBy": "tags"
    }
  }
}
